gently/__init__.py
gently/input.hy
gently/language.hy
gently/math.hy
gently/plot.hy
gently/response.hy
gently/tests.hy
gently/transfer_function.hy
gently/utils.hy
gently/variable.hy
gently-0.18.dist-info/LICENSE
gently-0.18.dist-info/METADATA
gently-0.18.dist-info/WHEEL
gently-0.18.dist-info/entry_points.txt
gently-0.18.dist-info/top_level.txt
gently-0.18.dist-info/RECORD
