Metadata-Version: 2.1
Name: gently
Version: 0.18
Summary: A tool for designing and analysing control systems
Home-page: https://github.com/celaleddin/gently/
Author: Celaleddin Hidayetoğlu
Author-email: celaleddin.hidayetoglu@gmail.com
License: MIT
Platform: UNKNOWN
Requires-Dist: hy
Requires-Dist: sympy
Requires-Dist: control
Requires-Dist: matplotlib
